o_bmi_cal/bmi.py
o_bmi_cal-0.0.0.3.dist-info/METADATA
o_bmi_cal-0.0.0.3.dist-info/WHEEL
o_bmi_cal-0.0.0.3.dist-info/top_level.txt
o_bmi_cal-0.0.0.3.dist-info/RECORD
